py2p/__init__.py
py2p/__main__.py
py2p/base.py
py2p/chord.py
py2p/flags.py
py2p/ford.py
py2p/mesh.py
py2p/messages.py
py2p/seeders.msgpack
py2p/ssl_wrapper.py
py2p/sync.py
py2p/utils.py
py2p/test/__init__.py
py2p/test/test_base.py
py2p/test/test_cbase.py
py2p/test/test_chord.py
py2p/test/test_mesh.py
py2p/test/test_messages.py
py2p/test/test_sync.py
py2p/test/test_utils.py
py2p-0.7.878.dist-info/METADATA
py2p-0.7.878.dist-info/RECORD
py2p-0.7.878.dist-info/WHEEL
py2p-0.7.878.dist-info/entry_points.txt
py2p-0.7.878.dist-info/top_level.txt
