Metadata-Version: 2.1
Name: py2p
Version: 0.7.878
Summary: A python library for peer-to-peer networking
Home-page: https://github.com/gappleto97/p2p-project
Author: Gabe Appleton
Author-email: gappleto97+development@gmail.com
License: LGPLv3
Platform: UNKNOWN
Classifier: Development Status :: 4 - Beta
Classifier: Intended Audience :: Developers
Classifier: License :: OSI Approved :: GNU Lesser General Public License v3 (LGPLv3)
Classifier: Operating System :: OS Independent
Classifier: Topic :: Communications
Classifier: Topic :: Internet
Classifier: Programming Language :: C
Classifier: Programming Language :: C++
Classifier: Programming Language :: JavaScript
Classifier: Programming Language :: Other
Classifier: Programming Language :: Python
Classifier: Programming Language :: Python :: 2
Classifier: Programming Language :: Python :: 3
Classifier: Programming Language :: Python :: 2.7
Classifier: Programming Language :: Python :: 3.3
Classifier: Programming Language :: Python :: 3.4
Classifier: Programming Language :: Python :: 3.5
Classifier: Programming Language :: Python :: 3.6
Provides-Extra: snappy
Provides-Extra: SSL
Requires-Dist: custom-inherit
Requires-Dist: async-promises
Requires-Dist: u-msgpack-python
Requires-Dist: pyee
Requires-Dist: typing
Requires-Dist: base58
Provides-Extra: SSL
Requires-Dist: cryptography; extra == 'SSL'
Provides-Extra: snappy
Requires-Dist: python-snappy; extra == 'snappy'
